pytftk/__init__.py
pytftk/arrays.py
pytftk/autocorrelation.py
pytftk/dicts.py
pytftk/distribute.py
pytftk/formatting.py
pytftk/gpu_tools.py
pytftk/logbooks.py
pytftk/math.py
pytftk/nn.py
pytftk/runs_management.py
pytftk/sequence.py
pytftk-1.0.dist-info/METADATA
pytftk-1.0.dist-info/WHEEL
pytftk-1.0.dist-info/top_level.txt
pytftk-1.0.dist-info/RECORD
